[
  {
    "desc": "Insert semicolon at the end of the line in insert mode",
    "plugin": "none",
    "key": "<leader>;",
    "action": "<Esc>mlA;<Esc>`la",
    "mode": [
      "i"
    ]
  },
  {
    "desc": "Insert semicolon at the end of the line in normal mode",
    "plugin": "none",
    "key": "<leader>;",
    "action": "mlA;<Esc>`l",
    "mode": [
      "n"
    ]
  },
  {
    "desc": "Insert comma at the end of the line in insert mode",
    "plugin": "none",
    "key": "<leader><leader>",
    "action": "<Esc>mlA,<Esc>`la",
    "mode": [
      "i"
    ]
  },
  {
    "desc": "Insert comma at the end of the line in normal mode",
    "plugin": "none",
    "key": "<leader><leader>",
    "action": "mlA,<Esc>`l",
    "mode": [
      "n"
    ]
  },
  {
    "desc": "Scroll down and center cursor",
    "plugin": "none",
    "key": "<C-d>",
    "action": "<C-d>zz",
    "mode": [
      "n"
    ]
  },
  {
    "desc": "Scroll up and center cursor",
    "plugin": "none",
    "key": "<C-u>",
    "action": "<C-u>zz",
    "mode": [
      "n"
    ]
  },
  {
    "desc": "Move to next search result and center cursor",
    "plugin": "none",
    "key": "n",
    "action": "nzzv",
    "mode": [
      "n"
    ]
  },
  {
    "desc": "Move to previous search result and center cursor",
    "plugin": "none",
    "key": "N",
    "action": "Nzzv",
    "mode": [
      "n"
    ]
  },
  {
    "desc": "Print all the keymaps registered",
    "plugin": "none",
    "key": "<leader>csm",
    "action": "function",
    "mode": [
      "n"
    ]
  },
  {
    "desc": "Paste before and send to black hole",
    "plugin": "none",
    "key": "<leader>p",
    "action": "\"_dP",
    "mode": [
      "x"
    ]
  },
  {
    "desc": "Paste after and send to black hole",
    "plugin": "none",
    "key": "<leader>d",
    "action": "\"_dp",
    "mode": [
      "n"
    ]
  },
  {
    "desc": "Paste after and send to black hole",
    "plugin": "none",
    "key": "<leader>d",
    "action": "\"_dp",
    "mode": [
      "v"
    ]
  },
  {
    "desc": "Move to the pane above",
    "plugin": "none",
    "key": "<c-k>",
    "action": ":wincmd k<CR>",
    "mode": [
      "n"
    ]
  },
  {
    "desc": "Move to the pane below",
    "plugin": "none",
    "key": "<c-j>",
    "action": ":wincmd j<CR>",
    "mode": [
      "n"
    ]
  },
  {
    "desc": "Move to the pane to the left",
    "plugin": "none",
    "key": "<c-h>",
    "action": ":wincmd h<CR>",
    "mode": [
      "n"
    ]
  },
  {
    "desc": "Move to the pane to the right",
    "plugin": "none",
    "key": "<c-l>",
    "action": ":wincmd l<CR>",
    "mode": [
      "n"
    ]
  },
  {
    "desc": "Source the vim configuration file",
    "plugin": "none",
    "key": "<leader>vs",
    "action": "<cmd>source $MYVIMRC<CR>",
    "mode": [
      "n"
    ]
  },
  {
    "desc": "Edit the vim configuration file",
    "plugin": "none",
    "key": "<leader>ve",
    "action": "<cmd>e $MYVIMRC<CR>",
    "mode": [
      "n"
    ]
  },
  {
    "desc": "Format the code of the current file using LSP [none-ls]",
    "plugin": "none-ls",
    "key": "<leader>fc",
    "action": "function",
    "mode": [
      "n"
    ]
  },
  {
    "desc": "Open documentation pane for symbol under cursor",
    "plugin": "nvim-lspconfig",
    "key": "<leader>d",
    "action": "function",
    "mode": [
      "n"
    ]
  },
  {
    "desc": "Go to definition of symbol under cursor",
    "plugin": "nvim-lspconfig",
    "key": "<leader>gt",
    "action": "function",
    "mode": [
      "n"
    ]
  },
  {
    "desc": "Go to implementation of symbol under cursor",
    "plugin": "nvim-lspconfig",
    "key": "<leader>gi",
    "action": "function",
    "mode": [
      "n"
    ]
  },
  {
    "desc": "Open the code actions pane to help fix errors in your code",
    "plugin": "nvim-lspconfig",
    "key": "<leader>ca",
    "action": "function",
    "mode": [
      "n"
    ]
  },
  {
    "desc": "Rename the symbol under the cursor",
    "plugin": "nvim-lspconfig",
    "key": "<leader>rn",
    "action": "function",
    "mode": [
      "n"
    ]
  },
  {
    "desc": "Telescope find git files [telescope.nvim]",
    "plugin": "telescope.nvim",
    "key": "<C-p>",
    "action": "function",
    "mode": [
      "n"
    ]
  },
  {
    "desc": "Telescope find files [telescope.nvim]",
    "plugin": "telescope.nvim",
    "key": "<C-P>",
    "action": "function",
    "mode": [
      "n"
    ]
  },
  {
    "desc": "Telescope live grep [telescope.vim]",
    "plugin": "telescope.vim",
    "key": "<leader>fg",
    "action": "function",
    "mode": [
      "n"
    ]
  },
  {
    "desc": "Telescope vim buffers [telescope.vim]",
    "plugin": "telescope.vim",
    "key": "<leader>fb",
    "action": "function",
    "mode": [
      "n"
    ]
  },
  {
    "desc": "Preview Git hunk [gitsigns.nvim]",
    "plugin": "gitsigns.nvim",
    "key": "<leader>gp",
    "action": ":Gitsigns preview_hunk<CR>",
    "mode": [
      "n"
    ]
  },
  {
    "desc": "Search for a session [rmagatti/auto-session]",
    "plugin": "auto-session",
    "key": "<leader>ls",
    "action": "function",
    "mode": [
      "n"
    ]
  },
  {
    "desc": "Navigate to the left tmux pane [vim-tmux-navigator]",
    "plugin": "vim-tmux-navigator",
    "key": "<c-h>",
    "action": "<cmd>TmuxNavigateLeft<cr>",
    "mode": [
      "n"
    ]
  },
  {
    "desc": "Navigate to the bottom tmux pane [vim-tmux-navigator]",
    "plugin": "vim-tmux-navigator",
    "key": "<c-j>",
    "action": "<cmd>TmuxNavigateDown<cr>",
    "mode": [
      "n"
    ]
  },
  {
    "desc": "Navigate to the top tmux pane [vim-tmux-navigator]",
    "plugin": "vim-tmux-navigator",
    "key": "<c-k>",
    "action": "<cmd>TmuxNavigateUp<cr>",
    "mode": [
      "n"
    ]
  },
  {
    "desc": "Navigate to the right tmux pane [vim-tmux-navigator]",
    "plugin": "vim-tmux-navigator",
    "key": "<c-l>",
    "action": "<cmd>TmuxNavigateRight<cr>",
    "mode": [
      "n"
    ]
  },
  {
    "desc": "Navigate to the previous tmux pane [vim-tmux-navigator]",
    "plugin": "vim-tmux-navigator",
    "key": "<c-\\>",
    "action": "<cmd>TmuxNavigatePrevious<cr>",
    "mode": [
      "n"
    ]
  },
  {
    "desc": "Ask copilot [CopilotC-Nvim/CopilotChat.nvim]",
    "plugin": "CopilotChat",
    "key": "<leader>cop",
    "action": "function",
    "mode": [
      "n",
      "v"
    ]
  },
  {
    "desc": "Ask copilot for a file [CopilotC-Nvim/CopilotChat.nvim]",
    "plugin": "CopilotChat",
    "key": "<leader>cof",
    "action": "function",
    "mode": [
      "n",
      "v"
    ]
  },
  {
    "desc": "Ask copilot for a help [CopilotC-Nvim/CopilotChat.nvim]",
    "plugin": "CopilotChat",
    "key": "<leader>coh",
    "action": "function",
    "mode": [
      "n",
      "v"
    ]
  },
  {
    "desc": "Run the nearest test [vim-test]",
    "plugin": "vim-test",
    "key": "<leader>t",
    "action": ":TestNearest<CR>",
    "mode": [
      "n"
    ]
  },
  {
    "desc": "Run all tests in the current file [vim-test]",
    "plugin": "vim-test",
    "key": "<leader>T",
    "action": ":TestFile<CR>",
    "mode": [
      "n"
    ]
  },
  {
    "desc": "Run the entire test suite [vim-test]",
    "plugin": "vim-test",
    "key": "<leader>A",
    "action": ":TestSuite<CR>",
    "mode": [
      "n"
    ]
  },
  {
    "desc": "Run the last test [vim-test]",
    "plugin": "vim-test",
    "key": "<leader>l",
    "action": ":TestLast<CR>",
    "mode": [
      "n"
    ]
  },
  {
    "desc": "Visit the last test file [vim-test]",
    "plugin": "vim-test",
    "key": "<leader>g",
    "action": ":TestVisit<CR>",
    "mode": [
      "n"
    ]
  },
  {
    "desc": "Toggle Neotree file explorer [neo-tree.nvim]",
    "plugin": "neo-tree.nvim",
    "key": "<leader>nt",
    "action": ":Neotree toggle<CR>",
    "mode": [
      "n"
    ]
  },
  {
    "desc": "Add file to Harpoon list",
    "plugin": "harpoon",
    "key": "<leader>a",
    "action": "function",
    "mode": [
      "n"
    ]
  },
  {
    "desc": "Toggle Harpoon list",
    "plugin": "harpoon",
    "key": "<C-e>",
    "action": "function",
    "mode": [
      "n"
    ]
  },
  {
    "desc": "Select 1st file in Harpoon list",
    "plugin": "harpoon",
    "key": "<leader>q",
    "action": "function",
    "mode": [
      "n"
    ]
  },
  {
    "desc": "Select 2nd file in Harpoon list",
    "plugin": "harpoon",
    "key": "<leader>w",
    "action": "function",
    "mode": [
      "n"
    ]
  },
  {
    "desc": "Select 3rd file in Harpoon list",
    "plugin": "harpoon",
    "key": "<leader>e",
    "action": "function",
    "mode": [
      "n"
    ]
  },
  {
    "desc": "Select 4th file in Harpoon list",
    "plugin": "harpoon",
    "key": "<leader>r",
    "action": "function",
    "mode": [
      "n"
    ]
  },
  {
    "desc": "Go to previous file in Harpoon list",
    "plugin": "harpoon",
    "key": "<S-Q>",
    "action": "function",
    "mode": [
      "n"
    ]
  },
  {
    "desc": "Go to next file in Harpoon list",
    "plugin": "harpoon",
    "key": "<S-W>",
    "action": "function",
    "mode": [
      "n"
    ]
  },
  {
    "desc": "Show Git blame for the current file [vim-fugitive]",
    "plugin": "vim-fugitive",
    "key": "<leader>gb",
    "action": ":Git blame<CR>",
    "mode": [
      "n"
    ]
  }
]